[
null,
{"id":1,"animationId":-1,"damage":{"critical":true,"elementId":-1,"formula":"a.atk * 4 - b.def * 2","type":1,"variance":20},"description":"Damages the enemy.","effects":[{"code":21,"dataId":0,"value1":1,"value2":0}],"hitType":1,"iconIndex":106,"message1":" attacks!","message2":"","mpCost":0,"name":"Attack","note":"Skill #1 will be used when you select\nthe Attack command.\n\n\\left(a\\cdot4-d\\right)-\\left(t-s\\right)\na= attack\nd= def\ns= strength\nt= armor","occasion":1,"repeats":1,"requiredWtypeId1":0,"requiredWtypeId2":0,"scope":1,"speed":0,"stypeId":0,"successRate":100,"tpCost":0,"tpGain":5},
{"id":2,"animationId":0,"damage":{"critical":false,"elementId":0,"formula":"0","type":0,"variance":20},"description":"Protects user and reduces damage taken.","effects":[{"code":21,"dataId":9,"value1":1,"value2":0}],"hitType":0,"iconIndex":171,"message1":" uses %1!","message2":"","mpCost":0,"name":"Guard","note":"Skill #2 will be used when you select\nthe Guard command.","occasion":1,"repeats":1,"requiredWtypeId1":0,"requiredWtypeId2":0,"scope":11,"speed":2000,"stypeId":0,"successRate":100,"tpCost":0,"tpGain":10},
{"id":3,"animationId":15,"damage":{"critical":true,"elementId":0,"formula":"a.atk * 8 - b.def * 2","type":1,"variance":20},"description":"Can stun enemies","effects":[{"code":21,"dataId":8,"value1":0.5,"value2":0}],"hitType":1,"iconIndex":9,"message1":" uses %1!","message2":"","mpCost":0,"name":"uppercut","note":"","occasion":1,"repeats":1,"requiredWtypeId1":0,"requiredWtypeId2":0,"scope":1,"speed":0,"stypeId":1,"successRate":100,"tpCost":20,"tpGain":0},
{"id":4,"animationId":21,"damage":{"critical":false,"elementId":0,"formula":"0","type":0,"variance":20},"description":"Move it, boy!\nCauses a whole set of reactions","effects":[{"code":21,"dataId":5,"value1":0.5,"value2":0},{"code":21,"dataId":11,"value1":0.2,"value2":0},{"code":21,"dataId":13,"value1":0.3,"value2":0}],"hitType":2,"iconIndex":9,"message1":" does %1!","message2":"","mpCost":20,"name":"Interpretive dance","note":"","occasion":1,"repeats":1,"requiredWtypeId1":0,"requiredWtypeId2":0,"scope":2,"speed":0,"stypeId":1,"successRate":100,"tpCost":0,"tpGain":0},
{"id":5,"animationId":13,"damage":{"critical":false,"elementId":0,"formula":"0","type":0,"variance":20},"description":"Single out an enemy and lower their defense.","effects":[{"code":32,"dataId":3,"value1":5,"value2":0}],"hitType":0,"iconIndex":9,"message1":" uses %1!","message2":"","mpCost":25,"name":"Scheme","note":"","occasion":0,"repeats":1,"requiredWtypeId1":0,"requiredWtypeId2":0,"scope":1,"speed":0,"stypeId":1,"successRate":100,"tpCost":0,"tpGain":20},
{"id":6,"animationId":0,"damage":{"critical":false,"elementId":0,"formula":"0","type":0,"variance":20},"description":"Enemy action. Causes enemy to flee from battle.","effects":[{"code":41,"dataId":0,"value1":0,"value2":0}],"hitType":0,"iconIndex":116,"message1":" flees.","message2":"","mpCost":0,"name":"Escape","note":"","occasion":1,"repeats":1,"requiredWtypeId1":0,"requiredWtypeId2":0,"scope":11,"speed":0,"stypeId":0,"successRate":100,"tpCost":0,"tpGain":0},
{"id":7,"animationId":0,"damage":{"critical":false,"elementId":0,"formula":"0","type":0,"variance":20},"description":"Does nothing.","effects":[],"hitType":0,"iconIndex":6,"message1":" waits.","message2":"","mpCost":0,"name":"Wait","note":"","occasion":1,"repeats":1,"requiredWtypeId1":0,"requiredWtypeId2":0,"scope":0,"speed":0,"stypeId":0,"successRate":100,"tpCost":0,"tpGain":4},
{"id":8,"animationId":16,"damage":{"critical":true,"elementId":-1,"formula":"a.atk * 10 - b.def * 8","type":1,"variance":20},"description":"Attack that does great damage if the target has\nlow defense","effects":[],"hitType":1,"iconIndex":235,"message1":" uses %1!","message2":"","mpCost":0,"name":"Super Slap","note":"","occasion":1,"repeats":1,"requiredWtypeId1":0,"requiredWtypeId2":0,"scope":1,"speed":0,"stypeId":1,"successRate":100,"tpCost":20,"tpGain":0},
{"id":9,"animationId":19,"damage":{"critical":true,"elementId":-1,"formula":"a.atk * 5","type":1,"variance":20},"description":"go all like WHOAZZAO and kick them all.","effects":[],"hitType":1,"iconIndex":217,"message1":" uses %1!","message2":"","mpCost":0,"name":"Karate Ball","note":"","occasion":0,"repeats":1,"requiredWtypeId1":0,"requiredWtypeId2":0,"scope":2,"speed":0,"stypeId":1,"successRate":100,"tpCost":30,"tpGain":0},
{"id":10,"animationId":16,"damage":{"critical":true,"elementId":-1,"formula":"a.atk * 5","type":1,"variance":20},"description":"Stronger normal attack that ignores defense","effects":[],"hitType":1,"iconIndex":234,"message1":" uses %1!","message2":"","mpCost":0,"name":"Super Punch","note":"","occasion":1,"repeats":1,"requiredWtypeId1":0,"requiredWtypeId2":0,"scope":1,"speed":0,"stypeId":1,"successRate":100,"tpCost":20,"tpGain":0},
{"id":11,"animationId":10,"damage":{"critical":true,"elementId":-1,"formula":"a.atk * 4 - b.def * 2","type":5,"variance":20},"description":"","effects":[],"hitType":2,"iconIndex":16,"message1":"","message2":"","mpCost":0,"name":"drain attack","note":"","occasion":0,"repeats":1,"requiredWtypeId1":0,"requiredWtypeId2":0,"scope":1,"speed":0,"stypeId":1,"successRate":100,"tpCost":20,"tpGain":0},
{"id":12,"animationId":7,"damage":{"critical":false,"elementId":0,"formula":"a.atk * 6","type":1,"variance":20},"description":"ignores defense completely","effects":[],"hitType":1,"iconIndex":9,"message1":" uses %1!","message2":"","mpCost":50,"name":"Eye stab","note":"","occasion":0,"repeats":1,"requiredWtypeId1":4,"requiredWtypeId2":0,"scope":1,"speed":0,"stypeId":1,"successRate":100,"tpCost":0,"tpGain":0},
{"id":13,"animationId":0,"damage":{"critical":false,"elementId":0,"formula":"a.atk * 8 - b.def * 4","type":1,"variance":20},"description":"attack + bleed","effects":[{"code":21,"dataId":22,"value1":0.5,"value2":0}],"hitType":1,"iconIndex":16,"message1":"","message2":"","mpCost":10,"name":"slash super","note":"","occasion":0,"repeats":2,"requiredWtypeId1":2,"requiredWtypeId2":0,"scope":1,"speed":0,"stypeId":1,"successRate":100,"tpCost":20,"tpGain":0},
{"id":14,"animationId":9,"damage":{"critical":true,"elementId":0,"formula":"a.atk * 8 - b.def * 2","type":1,"variance":20},"description":"massive damage","effects":[],"hitType":1,"iconIndex":177,"message1":" uses %1!","message2":"","mpCost":50,"name":"violence blast","note":"","occasion":0,"repeats":1,"requiredWtypeId1":0,"requiredWtypeId2":0,"scope":1,"speed":0,"stypeId":1,"successRate":100,"tpCost":0,"tpGain":0},
{"id":15,"animationId":1,"damage":{"critical":false,"elementId":0,"formula":"a.atk * 4 - b.def * 2","type":1,"variance":20},"description":"3 random attacks","effects":[],"hitType":1,"iconIndex":207,"message1":" uses %1!","message2":"","mpCost":0,"name":"crazy slaps","note":"","occasion":0,"repeats":1,"requiredWtypeId1":0,"requiredWtypeId2":0,"scope":5,"speed":0,"stypeId":1,"successRate":50,"tpCost":20,"tpGain":0},
{"id":16,"animationId":14,"damage":{"critical":false,"elementId":0,"formula":"a.atk * 4 - b.def * 2","type":5,"variance":20},"description":"bite someone as hard as you can and steal their life","effects":[],"hitType":1,"iconIndex":179,"message1":" goes for a nibble!","message2":"","mpCost":10,"name":"bite","note":"","occasion":0,"repeats":1,"requiredWtypeId1":0,"requiredWtypeId2":0,"scope":1,"speed":0,"stypeId":1,"successRate":100,"tpCost":0,"tpGain":0},
{"id":17,"animationId":0,"damage":{"critical":false,"elementId":0,"formula":"0","type":0,"variance":20},"description":"","effects":[{"code":21,"dataId":20,"value1":0.5,"value2":0}],"hitType":2,"iconIndex":16,"message1":" mushes about!","message2":"","mpCost":0,"name":"mushroom","note":"","occasion":0,"repeats":1,"requiredWtypeId1":0,"requiredWtypeId2":0,"scope":1,"speed":0,"stypeId":1,"successRate":100,"tpCost":0,"tpGain":0},
{"id":18,"animationId":13,"damage":{"critical":false,"elementId":0,"formula":"0","type":0,"variance":20},"description":"boosts attack for 5 turns","effects":[{"code":31,"dataId":2,"value1":5,"value2":0}],"hitType":2,"iconIndex":179,"message1":" uses %1!","message2":"","mpCost":30,"name":"get extremely mad for no reason","note":"","occasion":0,"repeats":1,"requiredWtypeId1":0,"requiredWtypeId2":0,"scope":11,"speed":0,"stypeId":1,"successRate":100,"tpCost":0,"tpGain":0},
{"id":19,"animationId":10,"damage":{"critical":false,"elementId":-1,"formula":"a.mat * 4 - b.mdf * 2","type":6,"variance":20},"description":"get everyone snotty and gross","effects":[{"code":21,"dataId":12,"value1":0.5,"value2":0},{"code":21,"dataId":11,"value1":0.5,"value2":0}],"hitType":2,"iconIndex":180,"message1":" uses %1!","message2":"","mpCost":30,"name":"Sneeze of fury","note":"","occasion":1,"repeats":1,"requiredWtypeId1":0,"requiredWtypeId2":0,"scope":3,"speed":0,"stypeId":1,"successRate":100,"tpCost":0,"tpGain":0},
{"id":20,"animationId":43,"damage":{"critical":false,"elementId":0,"formula":"0","type":0,"variance":20},"description":"","effects":[],"hitType":0,"iconIndex":180,"message1":" coughs!","message2":"","mpCost":0,"name":"cough","note":"","occasion":0,"repeats":1,"requiredWtypeId1":0,"requiredWtypeId2":0,"scope":0,"speed":0,"stypeId":1,"successRate":100,"tpCost":0,"tpGain":0},
{"id":21,"animationId":0,"damage":{"critical":false,"elementId":0,"formula":"0","type":0,"variance":20},"description":"","effects":[],"hitType":2,"iconIndex":0,"message1":" giggles.","message2":"","mpCost":0,"name":"laugh","note":"","occasion":0,"repeats":1,"requiredWtypeId1":0,"requiredWtypeId2":0,"scope":1,"speed":0,"stypeId":1,"successRate":100,"tpCost":0,"tpGain":0},
{"id":22,"animationId":115,"damage":{"critical":false,"elementId":0,"formula":"0","type":0,"variance":20},"description":"","effects":[{"code":32,"dataId":2,"value1":5,"value2":0}],"hitType":2,"iconIndex":0,"message1":" cries!","message2":"","mpCost":0,"name":"cry","note":"","occasion":0,"repeats":1,"requiredWtypeId1":0,"requiredWtypeId2":0,"scope":1,"speed":0,"stypeId":1,"successRate":100,"tpCost":0,"tpGain":0},
{"id":23,"animationId":23,"damage":{"critical":false,"elementId":0,"formula":"0","type":0,"variance":20},"description":"","effects":[{"code":21,"dataId":11,"value1":0.03,"value2":0}],"hitType":0,"iconIndex":0,"message1":" coughs!","message2":"","mpCost":0,"name":"secret cough","note":"","occasion":0,"repeats":1,"requiredWtypeId1":0,"requiredWtypeId2":0,"scope":2,"speed":0,"stypeId":1,"successRate":100,"tpCost":0,"tpGain":0},
{"id":24,"animationId":0,"damage":{"critical":false,"elementId":0,"formula":"0","type":0,"variance":20},"description":"","effects":[{"code":32,"dataId":4,"value1":5,"value2":0},{"code":32,"dataId":5,"value1":5,"value2":0}],"hitType":2,"iconIndex":0,"message1":" mopes around.","message2":"","mpCost":0,"name":"mope","note":"","occasion":0,"repeats":1,"requiredWtypeId1":0,"requiredWtypeId2":0,"scope":2,"speed":0,"stypeId":1,"successRate":100,"tpCost":0,"tpGain":0},
{"id":25,"animationId":27,"damage":{"critical":false,"elementId":-1,"formula":"a.atk * 2 - b.def * 2","type":1,"variance":20},"description":"throw dirt","effects":[{"code":21,"dataId":3,"value1":0.5,"value2":0}],"hitType":0,"iconIndex":219,"message1":" uses %1!","message2":"","mpCost":0,"name":"dirt throw","note":"","occasion":0,"repeats":1,"requiredWtypeId1":0,"requiredWtypeId2":0,"scope":1,"speed":0,"stypeId":1,"successRate":100,"tpCost":20,"tpGain":0},
{"id":26,"animationId":0,"damage":{"critical":false,"elementId":0,"formula":"0","type":2,"variance":20},"description":"","effects":[],"hitType":0,"iconIndex":181,"message1":"","message2":"","mpCost":0,"name":"Demonstrate","note":"","occasion":0,"repeats":1,"requiredWtypeId1":0,"requiredWtypeId2":0,"scope":1,"speed":0,"stypeId":1,"successRate":100,"tpCost":0,"tpGain":0},
{"id":27,"animationId":0,"damage":{"critical":false,"elementId":0,"formula":"0","type":0,"variance":20},"description":"","effects":[],"hitType":0,"iconIndex":0,"message1":"","message2":"","mpCost":40,"name":"native american rug burn","note":"","occasion":0,"repeats":9,"requiredWtypeId1":0,"requiredWtypeId2":0,"scope":1,"speed":0,"stypeId":1,"successRate":100,"tpCost":0,"tpGain":2},
{"id":28,"animationId":46,"damage":{"critical":false,"elementId":1,"formula":"200","type":1,"variance":0},"description":"it does.","effects":[],"hitType":0,"iconIndex":184,"message1":" does the %1!","message2":"","mpCost":50,"name":"attack that does 200 damage","note":"","occasion":0,"repeats":1,"requiredWtypeId1":0,"requiredWtypeId2":0,"scope":1,"speed":0,"stypeId":1,"successRate":100,"tpCost":0,"tpGain":0},
{"id":29,"animationId":0,"damage":{"critical":false,"elementId":0,"formula":"0","type":0,"variance":20},"description":"Call for a pit-stop\nEveryone heals 25%","effects":[],"hitType":0,"iconIndex":155,"message1":"","message2":"","mpCost":100,"name":"Pit stop","note":"","occasion":0,"repeats":1,"requiredWtypeId1":0,"requiredWtypeId2":0,"scope":1,"speed":0,"stypeId":1,"successRate":100,"tpCost":0,"tpGain":0},
{"id":30,"animationId":0,"damage":{"critical":false,"elementId":0,"formula":"0","type":0,"variance":20},"description":"will trip on next attack","effects":[{"code":21,"dataId":29,"value1":1,"value2":0}],"hitType":0,"iconIndex":236,"message1":" does nothing suspicious at all.","message2":"does something that's not a single bit suspicious.","mpCost":25,"name":"Ban Appeal","note":"","occasion":0,"repeats":1,"requiredWtypeId1":0,"requiredWtypeId2":0,"scope":11,"speed":0,"stypeId":1,"successRate":100,"tpCost":0,"tpGain":0},
{"id":31,"animationId":0,"damage":{"critical":false,"elementId":0,"formula":"0","type":0,"variance":20},"description":"","effects":[{"code":21,"dataId":19,"value1":0.5,"value2":0}],"hitType":2,"iconIndex":184,"message1":" locks eyes.","message2":"","mpCost":0,"name":"vacant stare","note":"","occasion":0,"repeats":1,"requiredWtypeId1":0,"requiredWtypeId2":0,"scope":1,"speed":0,"stypeId":1,"successRate":100,"tpCost":0,"tpGain":0},
{"id":32,"animationId":9,"damage":{"critical":true,"elementId":3,"formula":"a.mat * 5 - b.mdf * 5","type":1,"variance":20},"description":"use the blast","effects":[],"hitType":2,"iconIndex":7,"message1":" uses %1!","message2":"","mpCost":50,"name":"silly blast","note":"","occasion":0,"repeats":1,"requiredWtypeId1":0,"requiredWtypeId2":0,"scope":1,"speed":0,"stypeId":1,"successRate":100,"tpCost":0,"tpGain":0},
{"id":33,"animationId":0,"damage":{"critical":false,"elementId":0,"formula":"0","type":0,"variance":20},"description":"","effects":[],"hitType":0,"iconIndex":0,"message1":" does %1!","message2":"","mpCost":0,"name":"Rally","note":"","occasion":0,"repeats":1,"requiredWtypeId1":0,"requiredWtypeId2":0,"scope":8,"speed":0,"stypeId":1,"successRate":100,"tpCost":0,"tpGain":0},
{"id":34,"animationId":0,"damage":{"critical":false,"elementId":0,"formula":"0","type":0,"variance":20},"description":"","effects":[],"hitType":0,"iconIndex":0,"message1":" gobbles.","message2":"","mpCost":0,"name":"gobble","note":"","occasion":0,"repeats":1,"requiredWtypeId1":0,"requiredWtypeId2":0,"scope":1,"speed":0,"stypeId":1,"successRate":100,"tpCost":0,"tpGain":0},
{"id":35,"animationId":0,"damage":{"critical":false,"elementId":0,"formula":"a.mat * 5 - b.mdf * 5","type":2,"variance":20},"description":"makes you think","effects":[],"hitType":2,"iconIndex":3,"message1":" uses %1!","message2":"","mpCost":30,"name":"ugly beam","note":"","occasion":0,"repeats":1,"requiredWtypeId1":0,"requiredWtypeId2":0,"scope":1,"speed":0,"stypeId":1,"successRate":100,"tpCost":0,"tpGain":0},
{"id":36,"animationId":0,"damage":{"critical":false,"elementId":0,"formula":"0","type":0,"variance":20},"description":"","effects":[],"hitType":0,"iconIndex":0,"message1":"","message2":"","mpCost":0,"name":"","note":"","occasion":0,"repeats":1,"requiredWtypeId1":0,"requiredWtypeId2":0,"scope":1,"speed":0,"stypeId":1,"successRate":100,"tpCost":0,"tpGain":0},
{"id":37,"animationId":0,"damage":{"critical":false,"elementId":0,"formula":"0","type":0,"variance":20},"description":"","effects":[],"hitType":0,"iconIndex":0,"message1":"","message2":"","mpCost":0,"name":"","note":"","occasion":0,"repeats":1,"requiredWtypeId1":0,"requiredWtypeId2":0,"scope":1,"speed":0,"stypeId":1,"successRate":100,"tpCost":0,"tpGain":0},
{"id":38,"animationId":0,"damage":{"critical":false,"elementId":0,"formula":"0","type":0,"variance":20},"description":"","effects":[],"hitType":0,"iconIndex":0,"message1":"","message2":"","mpCost":0,"name":"","note":"","occasion":0,"repeats":1,"requiredWtypeId1":0,"requiredWtypeId2":0,"scope":1,"speed":0,"stypeId":1,"successRate":100,"tpCost":0,"tpGain":0},
{"id":39,"animationId":0,"damage":{"critical":false,"elementId":0,"formula":"0","type":0,"variance":20},"description":"","effects":[],"hitType":0,"iconIndex":0,"message1":"","message2":"","mpCost":0,"name":"","note":"","occasion":0,"repeats":1,"requiredWtypeId1":0,"requiredWtypeId2":0,"scope":1,"speed":0,"stypeId":1,"successRate":100,"tpCost":0,"tpGain":0},
{"id":40,"animationId":0,"damage":{"critical":false,"elementId":0,"formula":"0","type":0,"variance":20},"description":"","effects":[],"hitType":0,"iconIndex":0,"message1":"","message2":"","mpCost":0,"name":"","note":"","occasion":0,"repeats":1,"requiredWtypeId1":0,"requiredWtypeId2":0,"scope":1,"speed":0,"stypeId":1,"successRate":100,"tpCost":0,"tpGain":0},
{"id":41,"animationId":0,"damage":{"critical":false,"elementId":0,"formula":"0","type":0,"variance":20},"description":"","effects":[],"hitType":0,"iconIndex":0,"message1":"","message2":"","mpCost":0,"name":"","note":"","occasion":0,"repeats":1,"requiredWtypeId1":0,"requiredWtypeId2":0,"scope":1,"speed":0,"stypeId":1,"successRate":100,"tpCost":0,"tpGain":0},
{"id":42,"animationId":0,"damage":{"critical":false,"elementId":0,"formula":"0","type":0,"variance":20},"description":"","effects":[],"hitType":0,"iconIndex":0,"message1":"","message2":"","mpCost":0,"name":"","note":"","occasion":0,"repeats":1,"requiredWtypeId1":0,"requiredWtypeId2":0,"scope":1,"speed":0,"stypeId":1,"successRate":100,"tpCost":0,"tpGain":0},
{"id":43,"animationId":0,"damage":{"critical":false,"elementId":0,"formula":"0","type":0,"variance":20},"description":"","effects":[],"hitType":0,"iconIndex":0,"message1":"","message2":"","mpCost":0,"name":"","note":"","occasion":0,"repeats":1,"requiredWtypeId1":0,"requiredWtypeId2":0,"scope":1,"speed":0,"stypeId":1,"successRate":100,"tpCost":0,"tpGain":0},
{"id":44,"animationId":0,"damage":{"critical":false,"elementId":0,"formula":"0","type":0,"variance":20},"description":"","effects":[],"hitType":0,"iconIndex":0,"message1":"","message2":"","mpCost":0,"name":"","note":"","occasion":0,"repeats":1,"requiredWtypeId1":0,"requiredWtypeId2":0,"scope":1,"speed":0,"stypeId":1,"successRate":100,"tpCost":0,"tpGain":0},
{"id":45,"animationId":0,"damage":{"critical":false,"elementId":0,"formula":"0","type":0,"variance":20},"description":"","effects":[],"hitType":0,"iconIndex":0,"message1":"","message2":"","mpCost":0,"name":"","note":"","occasion":0,"repeats":1,"requiredWtypeId1":0,"requiredWtypeId2":0,"scope":1,"speed":0,"stypeId":1,"successRate":100,"tpCost":0,"tpGain":0},
{"id":46,"animationId":0,"damage":{"critical":false,"elementId":0,"formula":"0","type":0,"variance":20},"description":"","effects":[],"hitType":0,"iconIndex":0,"message1":"","message2":"","mpCost":0,"name":"","note":"","occasion":0,"repeats":1,"requiredWtypeId1":0,"requiredWtypeId2":0,"scope":1,"speed":0,"stypeId":1,"successRate":100,"tpCost":0,"tpGain":0},
{"id":47,"animationId":0,"damage":{"critical":false,"elementId":0,"formula":"0","type":0,"variance":20},"description":"","effects":[],"hitType":0,"iconIndex":0,"message1":"","message2":"","mpCost":0,"name":"","note":"","occasion":0,"repeats":1,"requiredWtypeId1":0,"requiredWtypeId2":0,"scope":1,"speed":0,"stypeId":1,"successRate":100,"tpCost":0,"tpGain":0},
{"id":48,"animationId":0,"damage":{"critical":false,"elementId":0,"formula":"0","type":0,"variance":20},"description":"","effects":[],"hitType":0,"iconIndex":0,"message1":"","message2":"","mpCost":0,"name":"","note":"","occasion":0,"repeats":1,"requiredWtypeId1":0,"requiredWtypeId2":0,"scope":1,"speed":0,"stypeId":1,"successRate":100,"tpCost":0,"tpGain":0},
{"id":49,"animationId":0,"damage":{"critical":false,"elementId":0,"formula":"0","type":0,"variance":20},"description":"","effects":[],"hitType":0,"iconIndex":0,"message1":"","message2":"","mpCost":0,"name":"","note":"","occasion":0,"repeats":1,"requiredWtypeId1":0,"requiredWtypeId2":0,"scope":1,"speed":0,"stypeId":1,"successRate":100,"tpCost":0,"tpGain":0},
{"id":50,"animationId":0,"damage":{"critical":false,"elementId":0,"formula":"0","type":0,"variance":20},"description":"","effects":[],"hitType":0,"iconIndex":0,"message1":"","message2":"","mpCost":0,"name":"","note":"","occasion":0,"repeats":1,"requiredWtypeId1":0,"requiredWtypeId2":0,"scope":1,"speed":0,"stypeId":1,"successRate":100,"tpCost":0,"tpGain":0},
{"id":51,"animationId":0,"damage":{"critical":false,"elementId":0,"formula":"0","type":0,"variance":20},"description":"","effects":[],"hitType":0,"iconIndex":0,"message1":"","message2":"","mpCost":0,"name":"","note":"","occasion":0,"repeats":1,"requiredWtypeId1":0,"requiredWtypeId2":0,"scope":1,"speed":0,"stypeId":1,"successRate":100,"tpCost":0,"tpGain":0},
{"id":52,"animationId":0,"damage":{"critical":false,"elementId":0,"formula":"0","type":0,"variance":20},"description":"","effects":[],"hitType":0,"iconIndex":0,"message1":"","message2":"","mpCost":0,"name":"","note":"","occasion":0,"repeats":1,"requiredWtypeId1":0,"requiredWtypeId2":0,"scope":1,"speed":0,"stypeId":1,"successRate":100,"tpCost":0,"tpGain":0}
]